kappaprofiler/TODO.py
kappaprofiler/__init__.py
kappaprofiler/profiler.py
kappaprofiler/stopwatch.py
kappaprofiler/time_node.py
kappaprofiler-0.0.5.dist-info/LICENSE
kappaprofiler-0.0.5.dist-info/METADATA
kappaprofiler-0.0.5.dist-info/WHEEL
kappaprofiler-0.0.5.dist-info/top_level.txt
kappaprofiler-0.0.5.dist-info/RECORD
