Metadata-Version: 2.1
Name: kappaprofiler
Version: 0.0.5
Summary: simple profiling framwork with little overhead
Home-page: https://github.com/BenediktAlkin/KappaProfiler
Project-URL: Source Code, https://github.com/BenediktAlkin/KappaProfiler
Project-URL: Bug Tracker, https://github.com/BenediktAlkin/KappaProfiler/issues
Classifier: Programming Language :: Python :: 3
Classifier: License :: OSI Approved :: MIT License
Classifier: Operating System :: OS Independent
Requires-Python: >=3.6
License-File: LICENSE
